islab/__init__.py
islab/aicup.py
islab_opendeid-0.0.1.1.dist-info/METADATA
islab_opendeid-0.0.1.1.dist-info/WHEEL
islab_opendeid-0.0.1.1.dist-info/top_level.txt
islab_opendeid-0.0.1.1.dist-info/RECORD
